{
  "title": "Fotografi",
  "projects": [
    {
      "id": 101,
      "name": "Race",
      "description": "Laget av Adele 1IMA",
      "image": "/data/2025/images/100/101.jpg"
    },
    {
      "id": 102,
      "name": "Skjeart i to",
      "description": "Laget av Andrea Linningsvoll 3MKA",
      "image": "/data/2025/images/100/102.jpg"
    },
    {
      "id": 103,
      "name": "Golden Hour",
      "description": "Laget av Ayat Jawad 2MKB",
      "image": "/data/2025/images/100/103.jpg"
    },
    {
      "id": 104,
      "name": "Lidenskap",
      "description": "Laget av Jin Zheng 2MKB",
      "image": "/data/2025/images/100/104.jpg"
    },
    {
      "id": 105,
      "name": "Reptilhjernen",
      "description": "Laget av Pia Olea Kristoffersen 3MKA",
      "image": "/data/2025/images/100/105.jpg"
    },
    {
      "id": 106,
      "name": "En dag som aldri stilner",
      "description": "Laget av Theodor S Borge 3MKA",
      "image": "/data/2025/images/100/106.jpg"
    },
    {
      "id": 107,
      "name": "Ekstraordinært i Oslo sentrum",
      "description": "Laget av Annali Lilledahl Kahn 2MPB",
      "image": "/data/2025/images/100/107.jpg"
    },
    {
      "id": 108,
      "name": "Etterlatt",
      "description": "Laget av Joakim Ellingsen 2MPB",
      "image": "/data/2025/images/100/108.jpg"
    }
  ]
}
